colcon_cargo_ros2-0.3.2.dist-info/METADATA
colcon_cargo_ros2-0.3.2.dist-info/WHEEL
colcon_cargo_ros2-0.3.2.dist-info/entry_points.txt
colcon_cargo_ros2/__init__.py
colcon_cargo_ros2/cargo_ros2_py.cpython-310-darwin.so
colcon_cargo_ros2/package_augmentation/__init__.py
colcon_cargo_ros2/task/__init__.py
colcon_cargo_ros2/task/ament_cargo/__init__.py
colcon_cargo_ros2/task/ament_cargo/build.py
colcon_cargo_ros2/task/ament_cargo/test.py
colcon_cargo_ros2/workspace_bindgen.py
colcon_cargo_ros2-0.3.2.dist-info/RECORD
