Metadata-Version: 2.4
Name: colcon-cargo-ros2
Version: 0.3.2
Classifier: Development Status :: 3 - Alpha
Classifier: Environment :: Plugins
Classifier: Intended Audience :: Developers
Classifier: License :: OSI Approved :: Apache Software License
Classifier: Operating System :: MacOS
Classifier: Operating System :: Microsoft :: Windows
Classifier: Operating System :: POSIX
Classifier: Programming Language :: Python :: 3
Classifier: Programming Language :: Python :: 3.8
Classifier: Programming Language :: Python :: 3.9
Classifier: Programming Language :: Python :: 3.10
Classifier: Programming Language :: Python :: 3.11
Classifier: Programming Language :: Python :: 3.12
Classifier: Programming Language :: Rust
Classifier: Topic :: Software Development :: Build Tools
Classifier: Topic :: Software Development :: Code Generators
Classifier: Topic :: Scientific/Engineering
Requires-Dist: colcon-core
Requires-Dist: colcon-library-path
Requires-Dist: colcon-ros
Summary: Extension for colcon to build Rust ROS 2 packages with automatic binding generation and ament installation
Keywords: ROS,ROS2,Rust,colcon,build-tool,robotics,message-generation,bindings
Author-email: Lin Hsiang-Jui <jerry73204@gmail.com>
License: Apache-2.0
Requires-Python: >=3.8
Project-URL: Homepage, https://github.com/jerry73204/colcon-cargo-ros2
Project-URL: Repository, https://github.com/jerry73204/colcon-cargo-ros2
Project-URL: Documentation, https://github.com/jerry73204/colcon-cargo-ros2#readme
Project-URL: Issues, https://github.com/jerry73204/colcon-cargo-ros2/issues
Project-URL: Changelog, https://github.com/jerry73204/colcon-cargo-ros2/releases
